Workbook

Sheet Tu embudo
B1: Simulador del embudo · Academias y centros de formación
B2: Rellena solo las celdas amarillas con los números de un mes normal. Todo lo demás se calcula solo. Los números que vienen puestos son un EJEMPLO: cámbialos por los tuyos.
B3: Celda amarilla = dato tuyo | C3: Celda blanca = fórmula (no hace falta tocarla)
B5: 1 · Tu embudo de un mes normal
B6: Etapa | C6: Tu número al mes | D6: % que pasa desde la etapa anterior | E6: Personas que se pierden en este paso | F6: Qué contar
B7: Inversión en anuncios al mes (€) | C7: 1000 | F7: Lo que pagas a Meta, Google, TikTok… en un mes. Sin contar agencia ni diseño.
B8: Solicitudes de información que entran | C8: 30 | F8: Formularios, mensajes y llamadas que llegan de los anuncios en ese mes.
B9: Hablan contigo o agendan | C9: 25 | D9: =IFERROR(MIN(C9/C8,1),0) -> 0.83333333 | E9: =MAX(C8-C9,0) -> 5 | F9: Cuántas de esas solicitudes llegan a hablar con alguien de tu centro o reservan cita.
B10: Se presentan a la cita o visita | C10: 10 | D10: =IFERROR(MIN(C10/C9,1),0) -> 0.4 | E10: =MAX(C9-C10,0) -> 15 | F10: Cuántos vienen de verdad (presencial, videollamada o sesión informativa).
B11: Se matriculan | C11: 1 | D11: =IFERROR(MIN(C11/C10,1),0) -> 0.1 | E11: =MAX(C10-C11,0) -> 9 | F11: Matrículas pagadas que salen de esas solicitudes.
B12: Valor medio de un alumno (€) | C12: 1500 | F12: Lo que factura de media una matrícula (el curso completo, no la reserva).
B13: =IF(OR(C9>C8,C10>C9,C11>C10),"Ojo: cada etapa tiene que ser igual o menor que la anterior. Revisa los números amarillos.","")
B15: 2 · Lo que te dejan hoy los anuncios, cada mes
B16: Facturación al mes que sale de los anuncios | C16: =C11*C12 -> 1500 | E16: Matrículas × valor medio de un alumno.
B17: Cada euro invertido te devuelve (ROAS) | C17: =IFERROR(C16/C7,0) -> 1.5 | E17: Facturación ÷ inversión. Por debajo de 1 €, los anuncios no pagan ni su coste.
B18: Coste por alumno matriculado | C18: =IF(C11>0,C7/C11,"Sin matrículas") -> 1000 | E18: Inversión ÷ matrículas. Lo que te cuesta en anuncios cada alumno nuevo.
B19: Coste por solicitud de información | C19: =IFERROR(C7/C8,0) -> 33.333333 | E19: Inversión ÷ solicitudes.
B20: De solicitud a matrícula (conversión total) | C20: =IFERROR(C11/C8,0) -> 0.033333333 | E20: Matrículas ÷ solicitudes.
B21: Solicitudes que no acaban en matrícula | C21: =MAX(C8-C11,0) -> 29 | E21: Solicitudes pagadas que se quedan por el camino.
B22: Facturación que genera cada solicitud | C22: =IFERROR(C16/C8,0) -> 50 | E22: Si esta cifra es mayor que el coste por solicitud, cada solicitud perdida es dinero perdido.
B24: 3 · Dónde más pierdes
B25: =IF(C8<=0,"Rellena tus números arriba y aquí verás en qué paso se te queda más gente.","En el paso donde más gente se te queda: "&CHOOSE(MATCH(MAX(E9:E11),E9:E11,0),"de la solicitud a hablar contigo","de hablar contigo a presentarse a la cita","de presentarse a matricularse")&" — se pierden "&ROUND(MAX(E9:E11),1)&" de cada "&ROUND(C8,1)&" solicitudes al mes.") -> En el paso donde más gente se te queda: de hablar contigo a presentarse a la cita — se pierden 15 de cada 30 solicitudes al mes.
B26: =IF(C8<=0,"",CHOOSE(MATCH(MAX(E9:E11),E9:E11,0),"Lo que suele fallar aquí: se responde tarde y no se insiste. Revisa la hoja «Qué mirar», bloques 1 y 2.","Lo que suele fallar aquí: citas sin confirmar, sin recordatorio y sin recuperar al que falta. Revisa «Qué mirar», bloques 2 y 3.","Lo que suele fallar aquí: la propuesta se queda sin fecha y sin seguimiento. Revisa «Qué mirar», bloque 4.")) -> Lo que suele fallar aquí: citas sin confirmar, sin recordatorio y sin recuperar al que falta. Revisa «Qué mirar», bloques 2 y 3.
B28: 4 · Lo que vale cada punto de mejora, con tus números
B29: Paso | C29: Hoy | D29: +1 punto vale al mes | E29: +5 puntos valen al mes | F29: Cómo leerlo
B30: De solicitud a hablar contigo | C30: =D9 -> 0.83333333 | D30: =C8*0.01*D10*D11*C12 -> 18 | E30: =D30*5 -> 90 | F30: Una solicitud más de cada 100 que llega a hablar contigo, con el resto igual.
B31: De hablar contigo a presentarse | C31: =D10 -> 0.4 | D31: =C9*0.01*D11*C12 -> 37.5 | E31: =D31*5 -> 187.5 | F31: Una persona más de cada 100 que habla contigo y se presenta.
B32: De presentarse a matricularse | C32: =D11 -> 0.1 | D32: =C10*0.01*C12 -> 150 | E32: =D32*5 -> 750 | F32: Una matrícula más de cada 100 que vienen a la cita.
B33: No todos los puntos cuestan lo mismo de ganar: mover la asistencia o la respuesta suele depender de procesos (responder rápido, confirmar, recordar); la matrícula depende más de tu equipo y de tu oferta.
B35: ¿Quieres que lo miremos con tus números reales? Diagnóstico gratuito de 30 minutos: qualivo.io/diagnostico

Sheet Escenario
B1: Escenario: misma inversión, mismas solicitudes, mejores etapas
B2: Las celdas amarillas traen el escenario prudente (explicado abajo). Puedes sobrescribirlas con tus propios objetivos, en %. Todo lo demás sale de la hoja «Tu embudo».
B4: 1 · Tus etapas: hoy y con el objetivo
B5: Paso | C5: Hoy | D5: Objetivo (editable) | E5: Personas al mes hoy | F5: Personas al mes con el objetivo
B6: Solicitudes de información | E6: ='Tu embudo'!C8 -> 30 | F6: =E6 -> 30
B7: Hablan contigo o agendan | C7: ='Tu embudo'!D9 -> 0.83333333 | D7: =MAX(C7,MIN(0.95,C7+0.1)) -> 0.93333333 | E7: ='Tu embudo'!C9 -> 25 | F7: =F6*D7 -> 28
B8: Se presentan a la cita | C8: ='Tu embudo'!D10 -> 0.4 | D8: =MAX(C8,MIN(0.85,C8*1.5)) -> 0.6 | E8: ='Tu embudo'!C10 -> 10 | F8: =F7*D8 -> 16.8
B9: Se matriculan | C9: ='Tu embudo'!D11 -> 0.1 | D9: =C9 -> 0.1 | E9: ='Tu embudo'!C11 -> 1 | F9: =F8*D9 -> 1.68
B11: 2 · Lo que cambia
B12: Cada mes | C12: Hoy | D12: Con el objetivo | E12: Diferencia
B13: Alumnos matriculados al mes | C13: =E9 -> 1 | D13: =F9 -> 1.68 | E13: =IFERROR(D13-C13,"—") -> 0.68
B14: Facturación al mes | C14: =C13*'Tu embudo'!C12 -> 1500 | D14: =D13*'Tu embudo'!C12 -> 2520 | E14: =IFERROR(D14-C14,"—") -> 1020
B15: Cada euro invertido te devuelve (ROAS) | C15: =IFERROR(C14/'Tu embudo'!C7,0) -> 1.5 | D15: =IFERROR(D14/'Tu embudo'!C7,0) -> 2.52 | E15: =IFERROR(D15-C15,"—") -> 1.02
B16: Coste por alumno matriculado | C16: =IF(C13>0,'Tu embudo'!C7/C13,"—") -> 1000 | D16: =IF(D13>0,'Tu embudo'!C7/D13,"—") -> 595.2381 | E16: =IFERROR(D16-C16,"—") -> -404.7619
B18: Facturación extra al mes | D18: =E14 -> 1020
B19: Facturación extra al año | D19: =E14*12 -> 12240
B20: ="Pasas de "&ROUND(C13,1)&" a "&ROUND(D13,1)&" alumnos al mes con la misma inversión en anuncios y las mismas solicitudes." -> Pasas de 1 a 1.7 alumnos al mes con la misma inversión en anuncios y las mismas solicitudes.
B22: Cómo está hecho el escenario prudente
B23: • Hablan contigo o agendan: 10 puntos más que hoy (máximo 95 %). Es lo que mueve responder en minutos y hacer seguimiento.
B24: • Se presentan a la cita: tu asistencia de hoy × 1,5 (máximo 85 %). Es lo que mueven la confirmación, los recordatorios y recuperar al que falta.
B25: • Se matriculan: igual que hoy. No lo tocamos: depende sobre todo de tu equipo y de tu oferta.
B26: • Son estimaciones con tus números, no una promesa. Úsalas para decidir qué etapa arreglar primero.

Sheet Qué mirar
B1: Qué mirar en cada paso
B2: Cinco comprobaciones por bloque. Marca «Sí» o «No» en la columna amarilla: cada «No» es un sitio concreto por donde se te escapan alumnos. Empieza por el bloque de «Dónde más pierdes».
B4: # | C4: Comprobación | D4: ¿Lo haces? | E4: Notas
B6: 1 · De la solicitud a hablar contigo: velocidad de respuesta
B7: 1 | C7: ¿Respondes a cada solicitud en menos de 5 minutos en horario de atención?
B8: 2 | C8: ¿Las solicitudes que entran de noche o en fin de semana reciben respuesta automática y llamada a primera hora?
B9: 3 | C9: ¿Sabes cuánto tardas de media en responder? (mira las 10 últimas: hora de entrada y hora de primer contacto)
B10: 4 | C10: ¿Hay una persona responsable de responder cada día, también cuando está de vacaciones o en clase?
B11: 5 | C11: ¿Contestas por el mismo canal por el que te escribió (WhatsApp si escribió por WhatsApp)?
B12: 2 · De la primera respuesta a la cita: seguimiento
B13: 1 | C13: ¿Haces al menos 4-5 intentos (llamada + WhatsApp) antes de dar una solicitud por perdida?
B14: 2 | C14: ¿Los intentos están repartidos en días y horas distintos, no todos el mismo día?
B15: 3 | C15: ¿Cada solicitud tiene un estado apuntado (nueva, contactada, cita, perdida) en un sitio que ve todo el equipo?
B16: 4 | C16: ¿Propones una fecha y hora concretas en la conversación, en lugar de «ya me dices»?
B17: 5 | C17: ¿Recuperas a los que dijeron «ahora no» con un mensaje a las 2-4 semanas?
B18: 3 · De la cita a que se presente: plantones
B19: 1 | C19: ¿Confirmas cada cita el mismo día que se agenda, por escrito, con dirección o enlace?
B20: 2 | C20: ¿Mandas recordatorio el día antes y unas horas antes de la cita?
B21: 3 | C21: ¿El recordatorio pide respuesta («¿nos vemos mañana a las 18:00?») y no solo informa?
B22: 4 | C22: ¿Llamas en los primeros 10 minutos al que no se presenta y le das una nueva fecha?
B23: 5 | C23: ¿Sabes tu % de asistencia del último mes (se presentan ÷ agendan)?
B24: 4 · De la visita a la matrícula: propuesta con fecha
B25: 1 | C25: ¿Cada persona que viene se va con una propuesta concreta: curso, precio, forma de pago y fecha de inicio?
B26: 2 | C26: ¿Acordáis en la visita cuándo volvéis a hablar (día y hora), en lugar de «piénsatelo»?
B27: 3 | C27: ¿Haces seguimiento en las 48 horas siguientes a la visita?
B28: 4 | C28: ¿Hay una fecha límite real (inicio de grupo, plazas, convocatoria) y la cuentas sin inventarla?
B29: 5 | C29: ¿Apuntas por qué no se matricula el que no se matricula (precio, horario, fechas, no lo tiene claro)?
B30: 5 · Qué anuncio trae matrículas: medición
B31: 1 | C31: ¿Sabes de qué campaña o anuncio viene cada solicitud (formulario con origen, UTM o pregunta al alumno)?
B32: 2 | C32: ¿Sabes cuántas matrículas trajo cada campaña el mes pasado, no solo cuántas solicitudes?
B33: 3 | C33: ¿Calculas el coste por alumno matriculado de cada campaña, no solo el coste por solicitud?
B34: 4 | C34: ¿La plataforma de anuncios recibe de vuelta qué solicitudes acabaron en matrícula?
B35: 5 | C35: ¿Revisas estos números al menos una vez al mes antes de decidir dónde poner el presupuesto?
B37: =IF(COUNTA(D6:D35)=0,"Cuando marques las comprobaciones, aquí verás cuántos «No» tienes.","Tienes "&COUNTIF(D6:D35,"No")&" «No» de "&COUNTA(D6:D35)&" comprobaciones marcadas. Empieza por el bloque con más «No» dentro de tu paso más débil.") -> Cuando marques las comprobaciones, aquí verás cuántos «No» tienes.
B38: Guía completa con ejemplos y arreglos para esta semana: «Las 5 fugas entre el anuncio y la matrícula» (PDF que acompaña a esta hoja).
